ui/Jarvis_UI.py
ui/__init__.py
uijarv-1.0.0.dist-info/LICENSE
uijarv-1.0.0.dist-info/METADATA
uijarv-1.0.0.dist-info/WHEEL
uijarv-1.0.0.dist-info/top_level.txt
uijarv-1.0.0.dist-info/RECORD
