Metadata-Version: 2.1
Name: uijarv
Version: 1.0.0
Summary: Installs my jarvis code on your system
Home-page: UNKNOWN
Author: Aditya Garg
Author-email: adityagarg1165@gmail.com
License: UNKNOWN
Keywords: Jarvis,jarviswithgui
Platform: UNKNOWN
Classifier: Development Status :: 1 - Planning
Classifier: Intended Audience :: Developers
Classifier: Programming Language :: Python :: 3
Classifier: Operating System :: Microsoft :: Windows
License-File: LICENSE
Requires-Dist: pyttsx3
Requires-Dist: speechrecognition
Requires-Dist: wikipedia
Requires-Dist: Pyqt5
Requires-Dist: Pyqt5-tools
Requires-Dist: pyjokes
Requires-Dist: pyautogui
